coloured_spectra/__init__.py
coloured_spectra/_nbdev.py
coloured_spectra/coloured_spectra.py
coloured_spectra-0.0.11.dist-info/LICENSE
coloured_spectra-0.0.11.dist-info/METADATA
coloured_spectra-0.0.11.dist-info/WHEEL
coloured_spectra-0.0.11.dist-info/entry_points.txt
coloured_spectra-0.0.11.dist-info/top_level.txt
coloured_spectra-0.0.11.dist-info/RECORD
