Metadata-Version: 2.1
Name: coloured-spectra
Version: 0.0.11
Summary: Got a spectra? Use this to find what is the observed colour.
Home-page: https://github.com/YiweiMao/coloured_spectra/tree/master/
Author: Yiwei Mao
Author-email: ewaymao@gmail.com
License: Creative Commons Attribution 3.0 Australia License
Keywords: spectral spectra spectrum colour color coloured colored
Platform: UNKNOWN
Classifier: Development Status :: 3 - Alpha
Classifier: Intended Audience :: Developers
Classifier: Natural Language :: English
Classifier: Programming Language :: Python :: 3.6
Classifier: Programming Language :: Python :: 3.7
Classifier: Programming Language :: Python :: 3.8
Classifier: License :: Other/Proprietary License
Requires-Python: >=3.6
Requires-Dist: pip
Requires-Dist: packaging
Requires-Dist: numpy (>="^1.13.3")
Requires-Dist: matplotlib (>="^2.1.1")
Requires-Dist: tqdm
Requires-Dist: opencv-python
Requires-Dist: pandas
Requires-Dist: pillow
Requires-Dist: holoviews
Provides-Extra: dev
